yta_youtube/__init__.py
yta_youtube/api.py
yta_youtube/dataclasses.py
yta_youtube/enums.py
yta_youtube/regex.py
yta_youtube/video.py
yta_youtube-0.0.28.dist-info/licenses/LICENSE
yta_youtube-0.0.28.dist-info/METADATA
yta_youtube-0.0.28.dist-info/WHEEL
yta_youtube-0.0.28.dist-info/RECORD
