Metadata-Version: 2.4
Name: yta-youtube
Version: 0.0.28
Summary: Youtube Autonomous Youtube interaction module.
License-File: LICENSE
Author: danialcala94
Author-email: danielalcalavalera@gmail.com
Requires-Python: ==3.9
Classifier: Programming Language :: Python :: 3
Classifier: Programming Language :: Python :: 3.9
Requires-Dist: requests (>=0.0.1,<9.0.0)
Requires-Dist: yt_dlp (>=2025.1.26,<2099.0.0)
Requires-Dist: yta_constants (>=0.0.1,<1.0.0)
Requires-Dist: yta_file (>=0.0.1,<1.0.0)
Requires-Dist: yta_file_downloader (>=0.0.1,<1.0.0)
Requires-Dist: yta_programming (>=0.0.1,<1.0.0)
Requires-Dist: yta_subtitles_parser (>=0.0.1,<1.0.0)
Requires-Dist: yta_temp (>=0.0.1,<1.0.0)
